examples/clangformat.py
examples/customization.py
pyrsl-3.0.0.data/data/share/gtksourceview-3.0/language-specs/rsl.lang
rsl/__init__.py
rsl/__rsl_lextab.py
rsl/__rsl_parsetab.py
rsl/ast.py
rsl/eval.py
rsl/gen_erate.py
rsl/lint.py
rsl/parse.py
rsl/runtime.py
rsl/symtab.py
rsl/version.py
pyrsl-3.0.0.dist-info/AUTHORS
pyrsl-3.0.0.dist-info/LICENSE
pyrsl-3.0.0.dist-info/METADATA
pyrsl-3.0.0.dist-info/WHEEL
pyrsl-3.0.0.dist-info/top_level.txt
pyrsl-3.0.0.dist-info/RECORD
