Metadata-Version: 2.1
Name: pyrsl
Version: 3.0.0
Summary: Interpreter for the Rule Specification Language (RSL)
Home-page: https://github.com/xtuml/pyrsl
Author: John Törnblom
Author-email: john.tornblom@gmail.com
License: GPLv3
Keywords: rsl xtuml bridgepoint
Classifier: Development Status :: 4 - Beta
Classifier: Intended Audience :: Developers
Classifier: Topic :: Software Development :: Interpreters
Classifier: License :: OSI Approved :: GNU General Public License v3 (GPLv3)
Classifier: Programming Language :: Python :: 3 :: Only
Requires: ply
Requires: pyxtuml
License-File: LICENSE
License-File: AUTHORS
Requires-Dist: ply
Requires-Dist: pyxtuml
